{"chunk_definitions":[{"chunk_id":"casxix5ov3l0z","chunk_label":"unnamed-chunk-1","document_id":"2C06D4B0","expansion_state":0,"options":{"engine":null},"row":14,"row_count":1,"visible":true},{"chunk_id":"c2xt9srx1qpe3","chunk_label":"unnamed-chunk-2","document_id":"2C06D4B0","expansion_state":0,"options":{"engine":null},"row":19,"row_count":1,"visible":true},{"chunk_id":"ckt60f6jqejz9","chunk_label":"unnamed-chunk-3","document_id":"2C06D4B0","expansion_state":0,"options":{"engine":null},"row":25,"row_count":1,"visible":true}],"doc_write_time":1541578291}